{"est": {"mort": {"__e": [[["-Il", "est", "mort", "?", "-Je", "ne", "sais", "pas", "!"], "I don't know!"], [["-Il", "est", "mort", "il", "y", "a", "longtemps", "déjà", "."], "- He died a long time ago. - Joseph."], [["-Il", "est", "mort", ".", "On", "l", "'", "a", "trouvé", "ce", "matin", "."], "He was found this morning."]]}, "__e": [[["-Il", "est", "venu", "me", "voir", "mais", "je", "n'ai", "rien", "dit", "."], "-He came to see me, but I didn't say anything."], [["-Il", "est", "comme", "ça", "tout", "le", "temps", "avec", "toi", "?"], "Does he always treat you like this?"], [["-Il", "est", "pas", "là", ",", "mais", "moi", "je", "suis", "là", "."], "-He's not in... but I'm here."]]}, "n": {"a": {"__e": [[["-Il", "n", "'", "a", "pas", "de", "place", "dans", "ma", "vie"], "- He doesn't have a place in my life"], [["-Il", "n", "'", "a", "pas", "pu", "passer", "par", "là", ".", "Il", "doit", "toujours", "être", "en", "ville", "."], "- He's not been through here"], [["-Il", "n", "'", "a", "pas", "vu", "la", "lumière", "du", "jour", "dans", "un", "temps", "long", "."], "-He hasn't seen daylight in a long time."]]}, "y": {"__e": [[["-Il", "n", "'", "y", "en", "a", "nulle", "part", "ici", ",", "je", "ne", "crois", "pas", "."], "-There's nowhere here, I don't think."], [["-Il", "n", "'", "y", "a", "pas", "une", "place", "pour", "moi", "dans", "la", "voiture", "?"], "-There no room for me in your car?"], [["-Il", "n", "'", "y", "a", "pas", "que", "moi", "qui", "vais", "mourir", ".", "Vous", "allez", "mourir", "aussi", ".", "Avec", "tous", "ceux", "qui", "sont", "ici", "."], "I'm not the only one that dies in here, you'll all be dead."]]}, "__e": [[["-Il", "n", "'", "y", "a", "pas", "une", "place", "pour", "moi", "dans", "la", "voiture", "?"], "-There no room for me in your car?"], [["-Il", "n", "'", "a", "pas", "pu", "passer", "par", "là", ".", "Il", "doit", "toujours", "être", "en", "ville", "."], "- He's not been through here"], [["-Il", "n", "'", "y", "a", "pas", "que", "moi", "qui", "vais", "mourir", ".", "Vous", "allez", "mourir", "aussi", ".", "Avec", "tous", "ceux", "qui", "sont", "ici", "."], "I'm not the only one that dies in here, you'll all be dead."]]}, "ne": {"__e": [[["-Il", "ne", "m", "'", "a", "rien", "dit", ".", "Seule", "lui", "le", "sait", "."], "- She hasn't told me anything."], [["-Il", "ne", "t", "'", "a", "pas", "parlé", "de", "lui", "?", "-", "Non", ".", "Un", "bon", "point", "."], "- Didn't he tell you about himself?"], [["-Il", "ne", "le", "veut", "pas", ",", "mais", "il", "le", "peut", "."], "- Hedoesn't want to, but he can."]]}, "a": {"été": {"__e": [[["-Il", "a", "été", "tué", "à", "la", "place", "de", "Rose", "."], "He was gunning for Roe."], [["-Il", "a", "été", "bon", "avec", "moi", "."], "- He was kind to me."], [["-Il", "a", "été", "attaqué", "à", "la", "même", "heure", "où", "tu", "étais", "chez", "lui", "."], "- He got beat up about the same time you were there."]]}, "pas": {"__e": [[["-Il", "a", "pas", "de", "rendez-vous", "."], "- He hasn't got a date."], [["-Il", "a", "pas", "pu", "!", "``", "J'ai", "un", "cancer", "!"], "-It Was not! \"I have cancer!"], [["-Il", "a", "pas", "un", "mauvais", "coup", "de", "pied", "."], "He doesn't have a bad kick."]]}, "__e": [[["-Il", "a", "dû", "le", "dire", "à", "tout", "le", "monde", ",", "en", "fait", "."], "I think he told everyone."], [["-Il", "a", "dit", "qu'il", "avait", "quelque", "chose", "?", "-", "C'est", "ce", "qu'il", "a", "dit", "."], "- He said he had something?"], [["-Il", "a", "dit", "que", "tu", "voulais", "me", "connaître", ",", "mais", "si", "c'était", "le", "cas", ",", "il", "ne", "serait", "pas", "ici", ",", "alors", "qu'est-ce", "que", "vous", "voulez", "vraiment", "tous", "les", "deux", "?"], "-He said that you wanted a relationship with me, but if that were true, he wouldn't be here, so, what is it that the two of you really want?"]]}, "y": {"en": {"__e": [[["-Il", "y", "en", "a", "un", "ici", "aussi", "!"], "There's one right there!"], [["-Il", "y", "en", "a", "pas", "un", "qui", "en", "a", "mis", "une", "."], "-There is not one who has one."], [["-Il", "y", "en", "a", "une", "dans", "la", "police", "."], "- There is at the police."]]}, "a": {"__e": [[["-Il", "y", "a", "ce", "gars", ",", "il", "est", "vraiment", "bon", "."], "-There is this guy, he's really good."], [["-Il", "y", "a", "bien", "des", "gens", "que", "tu", "vois", "à", "l'école", "?"], "There must be people you see. At school or in the neighborhood."], [["-Il", "y", "a", "un", "truc", "qui", "ne", "va", "pas", ":"], "Many things could fit, but one doesn't."]]}, "__e": [[["-Il", "y", "a", "bien", "des", "gens", "que", "tu", "vois", "à", "l'école", "?"], "There must be people you see. At school or in the neighborhood."], [["-Il", "y", "en", "a", "pas", "un", "qui", "en", "a", "mis", "une", "."], "-There is not one who has one."], [["-Il", "y", "avait", "lui", "et", "la", "femme", "de", "mon", "père", "..."], "- It was him and my father's wife..."]]}, "faut": {"que": {"__e": [[["-Il", "faut", "que", "tu", "sois", "là", ",", "ce", "soir", ",", "à", "11", "h", "."], "He said you should be here tonight, at 11 p.m., and wait for him."], [["-Il", "faut", "que", "je", "parle", "à", "ma", "femme", ".", "Oh", "..."], "I must speak to my wife."], [["-Il", "faut", "que", "je", "te", "parle", "tout", "de", "suite", "."], "- I must speak with you."]]}, "__e": [[["-Il", "faut", "que", "tu", "sois", "là", ",", "ce", "soir", ",", "à", "11", "h", "."], "He said you should be here tonight, at 11 p.m., and wait for him."], [["-Il", "faut", "que", "je", "te", "parle", "tout", "de", "suite", "."], "- I must speak with you."], [["-Il", "faut", "que", "je", "parle", "à", "ma", "femme", ".", "Oh", "..."], "I must speak to my wife."]]}, "__l": 4}