{"la": {"balle": {"__e": [[["Et", "parce", "qu'il", "est", "cassé", "comme", "ça", ",", "quand", "je", "lance", "la", "balle", "ça", "donne", "un", "bon", "petit", "effet", "."], "Because it's broken that way, when I throw the football, it gives it a nice little zip."], [["Tu", "veux", "jouer", ",", "on", "se", "lance", "la", "balle", "ou", "un", "truc", "du", "genre", "."], "You wannaplay, I'll throw the ball with you or something."], [["Alors", "attends", "...", "Le", "chien", "lance", "la", "balle", ",", "et", "je", "fais", "quoi", "maintenant", "?"], "So wait... the dog throws the ball, and I do what now?"]]}, "__e": [[["Alors", "attends", "...", "Le", "chien", "lance", "la", "balle", ",", "et", "je", "fais", "quoi", "maintenant", "?"], "So wait... the dog throws the ball, and I do what now?"], [["si", "vous", "êtes", "toujours", "à", "fond", "pour", "ça", "dans", "deux", "mois", ",", "je", "lance", "la", "machine", "."], "if you feel this strongly a couple months down the road, I'll get the ball rolling."], [["Tu", "veux", "jouer", ",", "on", "se", "lance", "la", "balle", "ou", "un", "truc", "du", "genre", "."], "You wannaplay, I'll throw the ball with you or something."]]}, "le": {"__e": [[["Votre", "père", "avait", "sa", "lance", "le", "jour", "de", "votre", "accident", "?"], "Did your father have his lance with him the day you fought the bull?"], [["Bien", "que", ",", "encore", "une", "fois", ",", "ce", "soit", "toujours", "moi", "qui", "lance", "le", "truc", "."], "Although, again, it's always me who initiates it."], [["Parce", "que", "quand", "il", "lance", "le", "téléphone", ",", "elle", "fait", "comme", "ça", "."], "When you throw her your phone, she's like..."]]}, "dans": {"une": {"__e": [[["On", "se", "lance", "dans", "une", "fête", "."], "We're throwing a party."], [["Je", "les", "lance", "dans", "une", "heure", "."], "Launching them in an hour."], [["Et", "puis", "on", "se", "lance", "dans", "une", "danse", "de", "malade", "et", "tout", "le", "monde", "est", "là", "."], "And then we all break out into this big dance routine, and everyone is there."]]}, "le": {"__e": [[["Puis", ",", "j'ai", "trouvé", "le", "corps", "de", "Lance", "dans", "le", "jardin", "."], "And then I found Lance's body in the garden."], [["Oh", ",", "mon", "Dieu", ",", "il", "se", "lance", "dans", "le", "droit", "du", "spectacle", "."], "Oh, my God, he's going into entertainment law."], [["Ça", "veut", "dire", "qu'on", "se", "lance", "dans", "le", "jeu", "?"], "Does that mean we'll be playin', Dude?"]]}, "__e": [[["Je", "suis", "très", "heureux", "de", "pouvoir", "aider", "un", "jeune", "qui", "se", "lance", "dans", "la", "vie", "."], "I'm pleased to give a young man a start in life. Feel right at home."], [["Je", "ne", "sais", "pas", "pourquoi", "je", "me", "lance", "dans", "ce", "problème", "."], "I don't know why I'm going to all this trouble."], [["Et", "ne", "me", "dis", "pas", "de", "mettre", "une", "lance", "dans", "ta", "main", "."], "And don't tell me to put a spear in your hand."]]}, "des": {"__e": [[["Pourquoi", "tout", "le", "monde", "veut", "que", "je", "lance", "des", "trucs", "?"], "Why does everybody keep asking me to throw stuff?"], [["Y", "en", "a", "qui", "font", "ça", "dans", "la", "rue", ",", "et", "on", "leur", "lance", "des", "sous", "."], "Guys do this all the time on the streets, and people throw money at them."], [["Il", "y", "a", "un", "homme", "qui", "lance", "des", "choses", "."], "There's a man throwing things."]]}, "un": {"avis": {"__e": [[["Je", "veux", "qu'on", "lance", "un", "avis", "de", "recherche", "pour", "ce", "gars", "sur", "le", "champ", "!"], "I want an A. P. B. put out on this guy now!"], [["Tu", "es", "sûr", "que", "tu", "ne", "veux", "pas", "qu'on", "lance", "un", "avis", "de", "recherche", "?"], "Are you sure you don't want us to put out an APB on your car?"], [["Lance", "un", "avis", "de", "recherche", "sur", "la", "voiture", "avec", "un", "homme", "et", "une", "femme", "."], "Parker: let's put an apb out on the car.One male, one female passenger."]]}, "défi": {"__e": [[["Rose", ",", "je", "crois", "que", "votre", "mari", "chéri", "nous", "lance", "un", "défi", "."], "Rose, I believe your darling husband is setting us a challenge."], [["J'ai", "besoin", "que", "tu", "me", "lance", "un", "défi", "pour", "pouvoir", "le", "battre", "."], "I need you to dare me to fight him!"], [["On", "dirait", "que", "je", "vous", "lance", "un", "défi", ",", "et", "vous", "avez", "raison", "."], "I know this seems like I'm putting you on the spot and in fact I am."]]}, "__e": [[["Peut-être", "que", "je", "me", "lance", "un", "peu", "trop", "vite", "."], "Maybe I'm jumping into this too fast."], [["Tu", "sais", "quoi", ",", "il", "faut", "qu'on", "lance", "un", "truc", "sur", "lui"], "You know, we got to throw something at it."], [["Si", "vous", "dites", "``", "je", "''", "une", "autre", "fois", ",", "je", "vous", "lance", "un", "truc", "par", "la", "tête", "."], "Because if you say \"I\" one more time, I'm gonna actually hurl something at your head, I think."]]}, "une": {"recherche": {"__e": [[["Je", "lance", "une", "recherche", "avec", "les", "mots", "clés", ",", "je", "suis", "sûre", "de", "retrouver", "cette", "affaire", "."], "Let me just put in the right search words, and I'm sure we'll be able to track down her case."], [["Je", "lance", "une", "recherche", "?", "Elle", "a", "peut-être", "eu", "un", "accident", "."], "I can run an APB, maybe she had an accident."], [["Je", "lance", "une", "recherche", "pour", "sa", "voiture", ",", "il", "va", "bien", "finir", "par", "rentrer", "chez", "lui", "."], "Post an unmarked. I'm going to put a broadcast out on his vehicle.He's gotta come home sometime."]]}, "__e": [[["Si", "je", "lance", "une", "balle", "assez", "vite", ",", "je", "peux", "tuer", "quelqu'un", "?"], "Hey man, do you think if I throw a bullet fast enough, I can kill somebody?"], [["Je", "lance", "une", "recherche", "pour", "sa", "voiture", ",", "il", "va", "bien", "finir", "par", "rentrer", "chez", "lui", "."], "Post an unmarked. I'm going to put a broadcast out on his vehicle.He's gotta come home sometime."], [["-", "Peut-être", "qu'il", "joue", "avec", "nous", ",", "qu'il", "nous", "lance", "une", "balle", "pour", "voir", "si", "on", "va", "courir", "la", "chercher", "?"], "- Where is he going next? - Or is he just toying with us-- jerking our chain just to see if we'll jump?"]]}, "__l": 3}