{"de": {"coco": {"__e": [[["Você", "gosta", "da", "água", "de", "coco", "?"], "You like coconut milk?"], [["Como", "vai", "querer", "sua", "água", "de", "coco", "?"], "Is there any special way you like your coconut juice?"], [["Vai", "dizer", "à", "América", "toda", "que", "morreu", "pegando", "água", "de", "coco", "?"], "You're gonna let the American people know he got killed getting you coconut milk?"]]}, "esgoto": {"__e": [[["Água", ",", "água", "de", "esgoto", ",", "óleo"], "Water, Sewage, Oil"], [["O", "sangue", "do", "homem", "teria", "que", "estar", "cheio", "de", "água", "de", "esgoto", "para", "estar", "com", "você", "as", "semanas", "que", "virão", "e", "se", "manter", "a", "distância", "."], "A man's blood would have to be full of bilge water to be with you for the weeks to come and keep his distance."], [["O", "que", "quer", "que", "você", "é", "um", "grupo", "ou", "indivíduo", ",", "vamos", "fazer", "o", "nosso", "melhor", "para", "fornecê-lo", "com", "a", "mensagem", "precisa", "e", "abrangente", "sobre", "Bomba", "De", "Água", "De", "Esgoto", "!"], "Whatever you are a group or individual, we will do our best to provide you with accurate and comprehensive message about Sewage Water Pump!"]]}, "__e": [[["Nós", "vamos", "ter", "a", "nossa", "água", "de", "volta", "!"], "We'll get our water back!"], [["A", "água", "de", "todos", "."], "- Everyone's water."], [["Disse", "que", "nossa", "água", "de", "60", "a", "70", "%", "."], "Our 60-70% water has said."]]}, "e": {"a": {"__e": [[["Podem", "fazer", "a", "diferença", "entre", "a", "água", "e", "a", "sua", "cama", "."], "They can make the difference between the water and your own bed."], [["E", "a", "água", "e", "a", "comida", "?"], "Food and water?"], [["A", "água", "e", "a", "água", "."], "YOU MOVE A MUSCLE AND..."]]}, "wc": {"__e": [[["Esta", "casa", "de", "50,78", "m²", ",", "construída", "em", "1930", ",", "de", "2", "andares", "tem", "3", "quartos", "das", "quais", "2", "quartos", ",", "1", "sala", "de", "água", "e", "1", "wc", ".", "ela", "contém", "uma", "sala", "de", "estar", ".", "aquecimento", ":", "individual", "gás", "."], "This house / villa of 50,78 m² (about 546 ft²), built in 1930, on 2 levels has 3 rooms including 2 bedrooms, 1 shower room and 1 toilet. It has a living room. Heating : individual gaz."], [["Esta", "casa", "de", "200", "m²", ",", "construída", "em", "1900", ",", "de", "2", "andares", "tem", "9", "quartos", "das", "quais", "4", "quartos", ",", "1", "casa", "de", "banho", ",", "1", "sala", "de", "água", "e", "3", "WC", ".", "Ela", "contém", "uma", "sala", "de", "estar", ",", "uma", "sala", "de", "jantar", ",", "uma", "adega", "e", "um", "estacionamento", ".", "Aquecimento", ":", "individual", "gás", "."], "This house / villa of 200 m² (about 2150 ft²), built in 1900, on 2 levels has 9 rooms including 4 bedrooms, 1 bathroom, 1 shower room and 3 toilets. It has a living room, dining room, a cellar and a parking lot. Heating : individual gaz."], [["Este", "apartamento", "tem", "2", "quartos", "das", "quais", "1", "quarto", ",", "1", "sala", "de", "água", "e", "1", "WC", ".", "Ele", "contém", "uma", "sala", "de", "estar", ",", "uma", "kitchenette", "e", "um", "estacionamento", ".", "Ele", "está", "situado", "no", "primeiro", "andar", "com", "elevador", "."], "This apartment has 2 rooms including 1 bedroom, 1 shower room and 1 toilet. It has a living room, a kitchenette and a parking lot. It's located on the 2nd floor with a lift."]]}, "__e": [[["A", "água", "e", "a", "água", "."], "YOU MOVE A MUSCLE AND..."], [["Você", "tem", "a", "água", "e", "eu", "tenho", "um", "filho", "que", "sabe", "o", "que", "fazer", "."], "Now, there's none around for miles, and people around here need a mill. Now, you have the water."], [["Não", ",", "eu", "tenho", "a", "água", "E", "eu", "vou", "ficar", "com", "ela", "!"], "No, I have the water and I'll keep it!"]]}, "do": {"rio": {"__e": [[["Não", "consegue", "ver", "a", "água", "do", "Rio", "Amarelo", ",", "seguindo", "em", "direção", "ao", "mar", "sem", "retornar", "?"], "Can't you see the Yellow River's water, keeps flowing into the sea without returning?"], [["Nesta", "aldeia", ",", "as", "mulheres", "têm", "de", "andar", "muito", "longe", "para", "buscar", "água", "do", "rio", "e", "fazer", "a", "lavanderia", "."], "In this village, women have to walk far enough to get water from the river and do the laundry."], [["Vou", "tirar", "isso", "fora", ",", "mas", ",", "a", "água", "do", "rio", "nunca", "mais", "vai", "deixar", "branco", "novamente", "."], "I'll wrench it out, only I know river water will never get it this white again."]]}, "mar": {"__e": [[["-", "O", "que", "?", "Água", "do", "mar", "?"], "- What, the seawater?"], [["Senhor", ",", "é", "realmente", "só", "água", "do", "mar", ",", "só", "isso", ".", "Apenas", "..."], "Well, sir, really, it's just plain old ordinary seawater, that's all."], [["-", "Aqui", "está", "sua", "água", "do", "mar", ",", "senhor", "."], "- Here's your seawater, sir."]]}, "__e": [[["!", "Lá", "se", "foi", "à", "água", "do", "café", "!"], "Hey that's the water for our coffee!"], [["É", "a", "melhor", "água", "do", "mundo", "."], "It is the best water of the world"], [["Eu", "tenho", "mais", "água", "do", "que", "preciso", "."], "(MacGyver) I GOT MORE WATER THAN I NEED."]]}, "para": {"o": {"__e": [[["-", "Água", "para", "o", "meu", "cavalo", "e", "uma", "cama", "para", "passar", "a", "noite", "."], "- Water for my horse and a bed for the night. - We have no room."], [["Quero", "colocar", "um", "pouco", "de", "água", "para", "o", "café", "."], "I wanna put some water on for the coffee."], [["Preciso", "de", "água", "para", "o", "meu", "carro", "."], "I need water for my truck."]]}, "a": {"__e": [[["‘", "Água", "para", "a", "Vida", "’", "para", "além", "de", "2015"], "‘Water for Life’ Beyond 2015"], [["←", "‘", "Água", "para", "a", "Vida", "’", "para", "além", "de", "2015"], "← ‘Water for Life’ Beyond 2015"], [["‘", "Água", "para", "a", "Vida", "’", "para", "além", "de", "2015", "→"], "‘Water for Life’ Beyond 2015 →"]]}, "__e": [[["Eu", "disse", "para", "não", "dar", "água", "para", "ele", "!"], "I said no water for him!"], [["Você", "tem", "água", "para", "nós", "?"], "Have you water for us?"], [["Bem", "você", "tem", "que", "usar", "água", "para", "ser", "se", "você", "não", "..."], "Well you gotta use water to see if you don't ..."]]}, "quente": {"para": {"__e": [[["Desculpe", ",", "pode", "ligar", "um", "pouco", "a", "água", "quente", "para", "mim", "?"], "Excuse me, could you run a little more hot water for me?"], [["Alguém", "quer", "mais", "água", "quente", "para", "o", "café", "da", "manhã", "?"], "More hot water for breakfast, anyone?"], [["O", "senhor", "precisa", "de", "água", "quente", "para", "o", "banho", "?"], "Shall I bring hot water for the gentleman?"]]}, "e": {"__e": [[["Olhe", ",", "para", "você", "a", "bolsa", "de", "água", "quente", "e", "para", "mim", "não", "?"], "Oh, you have a hot water bottle and I don't?"], [["É", "água", "quente", "e", "te", "faz", "bem", "."], "It's hot water and it's good for you."], [["Como", "é", "que", "você", "têm", "água", "quente", "e", "nós", "não", "?"], "How come you guys have hot water?"]]}, "__e": [[["O", "sistema", "de", "água", "quente", "aqui", "é", "dos", "anos", "30", "."], "Hot water system here dates back to the '30s."], [["Como", "é", "que", "você", "têm", "água", "quente", "e", "nós", "não", "?"], "How come you guys have hot water?"], [["Tem", "que", "ter", "um", "pouco", "de", "água", "quente", "."], "Have to have some hot water."]]}, "é": {"um": {"__e": [[["Nossa", "água", "é", "um", "perigo", "para", "nossos", "bebês", "."], "Our water is a harzard to our infants"], [["Esta", "água", "é", "um", "presente", ".", "Eu", "também", "agradeço", "a", "quem", "está", "dando", "isso", "de", "graça", "."], "This water is a gift. I also thank whomever is giving this for free."], [["A", "água", "é", "um", "bem", "essencial", "."], "Water is an essential good."]]}, "o": {"__e": [[["A", "água", "é", "o", "sangue", "da", "terra", "."], "Water's the earth's blood."], [["ÁGUA", "É", "O", "NOSSO", "NEGÓCIO"], "ANYTHING WATER IS OUR BUSINESS"], [["A", "água", "é", "o", "nosso", "mundo", "."], "Water is our world."]]}, "__e": [[["A", "água", "é", "para", "todos", "."], "The water is for everyone."], [["Água", ".", "É", "tudo", "para", "você", "."], "It's all for you."], [["A", "água", ",", "é", "por", "aqui", "."], "The water's this way."]]}, "__l": 1}