{"c'est": {"__e": [[["D'habitude", ",", "c'est", "le", "jeune", "homme", "qui", "le", "fait", "en", "premier", "."], "A young man generally does that."], [["Vous", "vous", "y", "êtes", "mise", "plus", "tôt", "qu'on", "le", "fait", "d'habitude", ",", "c'est", "tout", "."], "You're just getting it out of your system a little early, that's all."], [["Pas", "comme", "d'habitude", ",", "c'est", "pour", "de", "bon", "cette", "fois", "."], "Notjust again, but through for keeps."]]}, "on": {"__e": [[["D'habitude", "on", "ne", "le", "fait", "pas", "."], "We don't usually do this."], [["Comme", "d'habitude", "on", "a", "essayé", "de", "changer", "la", "vie", "des", "gens", "."], "As usual, we've been out changing people's lives."], [["Quand", "on", "a", "une", "relation", "de", "ce", "genre", ",", "d'habitude", "on", "n'en", "parle", "pas", "."], "We were having an affair, mooney. That's not the kind of thing you talk about."]]}, "tu": {"__e": [[["-", "Plus", "que", "d'habitude", ",", "tu", "veux", "dire", "?"], "No women weighing us down."], [["Comme", "d'habitude", ",", "tu", "nous", "a", "bien", "mis", "dans", "la", "merde", "."], "As usual, you got us in some serious shit here."], [["Seulement", ",", "d'habitude", "...", "Tu", "me", "dis", "à", "peine", "bonjour", "...", "Comme", "tu", "me", "le", "dis", "."], "But usually you never even say hello to me, so I'm a bit disconcerted"]]}, "il": {"__e": [[["D'habitude", "il", "est", "tout", "le", "temps", "avec", "moi", "..."], "Because everywhere I go, Nicolau is with me."], [["Pour", "tout", "à", "l'heure", ",", "fais", "pas", "attention", ".", "D'habitude", ",", "il", "est", "pas", "comme", "ça", "."], "Don't worry about how he talked to you back there."], [["D'habitude", ",", "il", "n'est", "jamais", "chez", "nous", "mais", "depuis", "quelques", "jours", ",", "il", "est", "tout", "le", "temps", "avec", "moi", "."], "Normally he's never home. But lately I spend all day with him. I wonder if heaven's retribution might strike me later, right Roku?"]]}, "je": {"ne": {"__e": [[["-", "D'habitude", "je", "ne", "suis", "pas", "si", "..."], "I'm usually not so silly, but..."], [["D'habitude", ",", "je", "ne", "suis", "pas", "comme", "ça", "."], "I'm not like this. I hate myself like this."], [["D'habitude", ",", "je", "ne", "suis", "pas", "au", "courant", "de", "ces", "informations", "."], "- Yeah. I'm not usually privy to inside information."]]}, "suis": {"__e": [[["Je", "ne", "suis", "pas", "là", "d'habitude", ".", "Je", "suis", "rentré", "tôt", ".", "Je", "veux", "des", "informations", "."], "I'm not usually home to see you, but i got home early today, and i'd like some information."], [["D'habitude", ",", "je", "suis", "bon", "à", "cela", "."], "I usually have great way for these gadgets."], [["D'habitude", ",", "je", "suis", "tout", "à", "fait", "maître", "de", "moi", "."], "I'm usually of an extremely controlled nature."]]}, "__e": [[["D'habitude", ",", "je", "ne", "suis", "pas", "au", "courant", "de", "ces", "informations", "."], "- Yeah. I'm not usually privy to inside information."], [["D'habitude", ",", "je", "me", "sens", "si", "plein", "que", "je", "ne", "peux", "rien", "faire", "."], "You know, I usually feel so full I can't really do anything."], [["Vous", "avez", "pris", "plus", "que", "votre", "part", "comme", "d'habitude", ",", "je", "vois", "."], "You've had more than your share as usual, I see."]]}, "les": {"gens": {"__e": [[["D'habitude", ",", "les", "gens", "qui", "chantent", "savent", "parler", "."], "- She does talk? Generally people that can sing can talk."], [["D'habitude", ",", "les", "gens", "venaient", "pour", "deux", "mois", "..."], "People used to come for a couple of months."], [["D'habitude", "les", "gens", "défaillent", ",", "il", "a", "envoyé", "des", "places", "donc", "ça", "ne", "l", "'", "a", "pas", "trop", "ému", "."], "People usually fail, he sent places so it has not moved too."]]}, "__e": [[["D'habitude", ",", "les", "garçons", "se", "donnent", "moins", "de", "mal", "pour", "m'en", "faire", "voir", "."], "Usually guys... don't go to so much trouble..."], [["-", "Comme", "d'habitude", ",", "les", "gars", "?"], "You boys want your usual?"], [["-", "Comme", "d'habitude", ",", "les", "enfants", "?"], "- The usual, ducks? - Yes, please."]]}, "__l": 4}