{"le": {"__e": [[["Il", "faudra", "le", "faire", "dans", "un", "mois", ",", "puis", "dans", "trois", "et", "six", "mois", "."], "You should have one in a month, then in three and after six months."], [["Eh", "bien", ",", "il", "faudra", "le", "faire", "voir", "à", "quelqu'un", ",", "un", "de", "ces", "jour", "."], "Well, oughta have somebody check it out someday."], [["Il", "me", "faudra", "le", "temps", "de", "trouver", "quelqu'un", "autre", "."], "I'll need time to find someone else."]]}, "un": {"autre": {"__e": [[["Il", "te", "faudra", "un", "autre", "haut", "."], "Mmm. You're gonna need a new shirt."], [["Il", "me", "faudra", "un", "autre", "petit", "frère", "."], "Now I need to find another little brother."], [["Et", "moi", ",", "il", "me", "faudra", "un", "autre", "grand", "frère", "."], "And I need to find another big brother."]]}, "peu": {"__e": [[["Il", "me", "faudra", "un", "peu", "plus", "de", "temps", "pour", "prendre", "cette", "décision", "."], "I'll need a little more time to make this decision."], [["Il", "t", "'", "en", "faudra", "un", "peu", "plus", "pour", "faire", "35", "ans", "."], "- You might need a few more for 35."], [["On", "va", "te", "trouver", "quelque", "chose", ",", "mais", "il", "faudra", "un", "peu", "de", "temps", "."], "We'll get you set up somewheres, but it takes a little time."]]}, "__e": [[["Il", "vous", "faudra", "un", "ou", "deux", "jours", "avant", "de", "prendre", "en", "charge", "..."], "I imagine you'll want a day or two to adjust before you take over."], [["Il", "t", "'", "en", "faudra", "un", "peu", "plus", "pour", "faire", "35", "ans", "."], "- You might need a few more for 35."], [["On", "va", "te", "trouver", "quelque", "chose", ",", "mais", "il", "faudra", "un", "peu", "de", "temps", "."], "We'll get you set up somewheres, but it takes a little time."]]}, "que": {"je": {"__e": [[["Il", "faudra", "que", "je", "trouve", "autre", "chose", "à", "faire", "."], "- No. I'll have to find something else to do."], [["Il", "faudra", "que", "je", "regarde", ",", "mais", "c'est", "à", "peu", "près", "la", "même", "chose", "."], "I'll have to have a look at it, but it's probably basically the same thing. Good."], [["Un", "de", "ces", "jours", ",", "il", "faudra", "que", "je", "lui", "demande", "comment", "elle", "a", "fait", "."], "I must ask her how she did that sometime."]]}, "tu": {"__e": [[["C'est", "là", "?", "Il", "faudra", "que", "tu", "penses", "à", "changer", "..."], "You gonna have to change..."], [["Il", "faudra", "que", "tu", "penses", "pour", "nous", "deux", "."], "You have to think for both of us."], [["Il", "faudra", "que", "tu", "vois", "ça", "."], "You should see it."]]}, "__e": [[["Il", "faudra", "que", "ce", "soit", "un", "homme", "pour", "y", "faire", "face", "."], "Check. Just as long as he's man enough to overcome them."], [["Il", "faudra", "que", "je", "regarde", ",", "mais", "c'est", "à", "peu", "près", "la", "même", "chose", "."], "I'll have to have a look at it, but it's probably basically the same thing. Good."], [["Un", "de", "ces", "jours", ",", "il", "faudra", "que", "je", "lui", "demande", "comment", "elle", "a", "fait", "."], "I must ask her how she did that sometime."]]}, "faire": {"avec": {"__e": [[["Ce", "n'est", "pas", "parfait", ",", "mais", "il", "faudra", "faire", "avec", "."], "It isn't perfect but it will have to do."], [["Il", "faudra", "faire", "avec", "ce", "que", "nous", "avons", "."], "We'll have to make do with what we've got. What we've got isn't enough."], [["Mais", "tant", "que", "j", "''", "ai", "pas", "de", "travail", ",", "faudra", "faire", "avec", "."], "But until I've found a job, we'll have to manage like this."]]}, "mieux": {"__e": [[["Il", "faudra", "faire", "mieux", "que", "ça", "."], "It'll take a lot more than that."], [["Il", "faudra", "faire", "mieux", "que", "ça", "mon", "vieux", "."], "One time, and that's all? You're gonna have to do better than that."], [["Mais", "il", "te", "faudra", "faire", "mieux", "si", "tu", "veux", "mon", "argent", "."], "But you'll have to do better than that if you want to come into my money."]]}, "__e": [[["Il", "faudra", "faire", "comme", "vous", "pouvez", "pendant", "un", "jour", "ou", "deux", "."], "Just make do with what you've got for a couple of days."], [["Mais", "si", "vous", "venez", ",", "il", "faudra", "faire", "ce", "que", "je", "vous", "dis", "."], "But if you want to come, you'll have to come like I tell you, and on my terms."], [["Et", "si", "tout", "ça", "est", "vrai", ",", "il", "faudra", "faire", "confiance", "à", "quelqu'un", "."], "And if it's all true, you're gonna have to trust someone."]]}, "bien": {"que": {"__e": [[["Il", "faudra", "bien", "que", "je", "le", "fasse", ".", "Un", "jour", "ou", "l'autre", "."], "I have to do it, sooner or later."], [["-", "Il", "faudra", "bien", "que", "je", "pense", "ainsi", "."], "- I guess I'll have to, sir."], [["Écoute", ",", "il", "faudra", "bien", "que", "tu", "me", "parles", "un", "jour", ",", "je", "suis", "ton", "père", "."], "Look... ... you'regonnahavetotalk to me eventually, I'm your daddy."]]}, "plus": {"__e": [[["Il", "me", "faudra", "bien", "plus", "qu'une", "simple", "explication", "."], "You'd better be prepared to do more than that. Kirk out."], [["Il", "lui", "faudra", "bien", "plus", "que", "ça", "pour", "cette", "mission", "."], "He'll need a lot more than that for this job."], [["mais", "il", "vous", "faudra", "bien", "plus", "que", "deux", "stars", "télé", "comme", "nous", "."], "But you will need more than just two media icons like us."]]}, "__e": [[["Il", "le", "faudra", "bien", "un", "jour", ".", "Le", "plus", "tôt", "sera", "le", "mieux", "."], "Sooner or later you have to decide, and the sooner you face it the better."], [["Si", "on", "veut", "que", "ça", "marche", "entre", "nous", ",", "faudra", "bien", "faire", "avec", ",", "non", "?"], "If we want to make anything out of this, we gotta deal with it, right?"], [["Tu", "es", "quand", "même", "une", "femme", ",", "il", "te", "faudra", "bien", "un", "mari", "."], "You are still a woman, you should have a husband."]]}, "me": {"tuer": {"__e": [[["Non", ",", "si", "vous", "voulez", "m", "'", "arrêter", ",", "il", "faudra", "me", "tuer", "."], "you'll have to kill me to stop me!"], [["Si", "tu", "veux", "le", "tuer", ",", "il", "faudra", "me", "tuer", "aussi", "."], "If you kill him, you'll have to kill me too."], [["Si", "vous", "voulez", "le", "tuer", ",", "il", "faudra", "me", "tuer", "aussi", "."], "If you kill him, you will have to kill me."]]}, "passer": {"__e": [[["Il", "faudra", "me", "passer", "sur", "le", "corps", "!"], "Over my dead body!"], [["Il", "faudra", "me", "passer", "sur", "le", "corps", "."], "Convention! You'll go to the convention over my dead body."], [["Pour", "partir", ",", "il", "faudra", "me", "passer", "sur", "le", "corps", "."], "The only way you two are leaving... is over my dead body."]]}, "__e": [[["Si", "vous", "la", "voulez", ",", "il", "faudra", "me", "la", "prendre", "."], "You will have to take it from me."], [["Si", "vous", "la", "voulez", ",", "il", "faudra", "me", "la", "prendre", ",", "comme", "les", "autres", "."], "If you want it, you'll take it from me like any of the others got to."], [["Mais", "il", "faudra", "me", "faire", "confiance", "car", "je", "ne", "pourrais", "jamais", "rien", "te", "dire", "de", "ma", "vie", "avant", "toi", "."], "But you'll have to take my word for it, and allow me to be silent forever as to my life before we met."]]}, "__l": 4}