{"e": {"__e": [[["L'unico", "modo", "di", "scoprire", "quanto", "gravemente", ",", "e", "'", "fare", "come", "ti", "dico", "."], "The only way you'll find out how badly is by doing as you're told."], [["Ah", ",", "um", "...", "sono", "rimasto", "coinvolto", "in", "un", "brutto", "incidente", "...", "sono", "stato", "ferito", "gravemente", "e", "mi", "hanno", "detto", "che", "lei", "è", "la", "migliore", "per", "questo", "genere", "di", "cose"], "Ah, um... I was in a bad accident... severely injured, and they tell me that you're the best at this kind of thing."], [["Quando", "torno", "'", "dalla", "...", "prima", "guerra", ",", "era", "ferito", "gravemente", "...", "e", "credeva", "che", "tutto", "quello", "che", "gli", "era", "successo", "...", "non", "fosse", "servito", "a", "nulla", "."], "When he came back from the first war he was badly injured and felt like everything that had happened to him had been for nothing."]]}, "malata": {"__e": [[["Avete", "detto", "voi", "stessa", "che", "sua", "moglie", "e", "'", "gravemente", "malata", "."], "You said yourself his wife is gravely ill."], [["So", "che", "ha", "fatto", "tanta", "strada", "per", "il", "suo", "trapianto", "e", "so", "quanto", "sia", "importante", "per", "lei", ",", "ma", "forse", "lei", "non", "sa", "che", "lo", "stesso", "organo", "era", "stato", "destinato", "a", "una", "giovane", "donna", "gravemente", "malata", ",", "che", "ne", "ha", "molto", "più", "bisogno", "di", "lei", "."], "I know you've come a long way for your transplant, and I know how important it is to you, but what you may not know is that that same organ was promised to a young woman who is desperately sick, and in much greater need of it than you. You?"], [["Perchè", "avrei", "dovuto", "dirlo", "a", "un", "uomo", "che", "ha", "lasciato", "la", "sua", "ragazza", "gravemente", "malata", "per", "stare", "con", "In", "Jung", "?"], "Why would I tell so much to a man who abandoned a severely ill person and went back to In Jung?"]]}, "ferito": {"__e": [[["So", "solo", "che", "lei", "e", "'", "gravemente", "ferito", "e", "sembra", "che", "siano", "state", "ferite", "anche", "altre", "persone", "."], "I just know that you've been seriously injured, and it sounds like other people have been as well."], [["Sto", "dicendo", "che", "ci", "serve", "un", "nuovo", "piano", ",", "perche", "'", "la", "prossima", "volta", "qualcuno", "di", "noi", "sara", "'", "cosi", "'", "gravemente", "ferito", "da", "non", "riuscire", "a", "guarire", "."], "I'm saying we need a new. Plan, because next time, one of. Us is gonna be too hurt to heal."], [["Alle", "7", "di", "sera", ",", "la", "madre", "della", "vittima", "e", "'", "arrivata", "a", "casa", "e", "ha", "trovato", "il", "figlio", "gravemente", "ferito", "."], "At 7 pm last night the victim's mother came home and found her son severly injured."]]}, "malato": {"__e": [[["Vostro", "marito", "e", "'", "gravemente", "malato", "ma", "se", "ben", "curato", "e", "con", "un", "po", "'", "di", "fortuna", ",", "non", "c", "'", "e", "'", "ragione", "per", "cui", "non", "debba", "guarire", "."], "Your husband and 'seriously ill But if well maintained and with a little 'luck, there is no' why should not heal."], [["Gli", "dirai", "che", "io", "sono", "gravemente", "malato", ",", "ma", "che", "e", "tutto", "in", "ordine", "."], "You will tell him that I am gravely ill, but that all is in hand."], [["-", "Ti", "ho", "appena", "detto", "che", "potresti", "essere", "gravemente", "malato", "e", "hai", "sentito", "solo", "quello", "?"], "- I just told you that you might be severely ill, and that's all you heard?"]]}, "feriti": {"__e": [[["Il", "dottore", "è", "famoso", "per", "aver", "curato", "quel", "generale", ",", "ma", "in", "realtà", "ha", "salvato", "molti", "soldati", "gravemente", "feriti", "."], "The doctor's famous for treating that general, but in fact he saved a lot of badly wounded soldiers."], [["-", "Mi", "scusi", ",", "signor", "sindaco", ",", "ma", "sette", "componenti", "del", "suo", "staff", "sono", "morti", "e", "altri", "sono", "gravemente", "feriti", ",", "non", "crede", "di", "dover", "loro", "una", "risposta", "migliore", "di", "``", "è", "complicato", "''", "?"], "Excuse me, Mr. Mayor, but 7 of your staffers are dead and others severely injured. Don't you think you owe them a response beyond \"it's complicated\"?"], [["C", "'", "è", "stata", "una", "sparatoria", "tra", "la", "polizia", "e", "gli", "indagati", "Un", "ispettore", "è", "stato", "colpito", "a", "morte", "2", "poliziotti", "sono", "stati", "gravemente", "feriti", "."], "Shoot outs occur between the police and the suspects"]]}, "ferita": {"__e": [[["Abbiamo", "due", "ragazze", "in", "macchina", ",", "una", "gravemente", "ferita", ",", "da", "che", "parte", "vanno", "?"], "We got 2 girls in a car, one badly hurt. Which way do they go?"], [["Nostra", "madre", "era", "gravemente", "ferita", "e", "la", "gente", "si", "stava", "prendendo", "cura", "di", "noi", "."], "Our mother was heavily wounded and people were taking care of us."], [["Quando", "ha", "scoperto", "che", "la", "sua", "amica", "era", "rimasta", "gravemente", "ferita", ",", "si", "è", "...", "sentito", "in", "colpa", "?"], "When you found out that your friend had been seriously injured, did you feel bad?"]]}, "__l": 6}