{"e": {"__e": [[["Se", "ci", "fosse", "un", "incendio", "e", "tu", "potessi", "portare", "solo", "una", "cosa", ",", "quale", "sarebbe", "?"], "If there was a fire, and you could only take one thing What would it be?"], [["C", "'", "e", "'", "stato", "un", "incendio", "e", "lui", "e", "'", "morto", "."], "There was a fire, and he was gone."], [["E", "poi", "ha", "detto", "che", "non", "sei", "neanche", "piu", "'", "un", "eroe", ",", "perche", "'", "hai", "lasciato", "morire", "7", "bambini", "in", "un", "incendio", ".", "E", "poi", "..."], "And then he said that you're not even a hero anymore because you let 7 babies die in a fire.And then..."]]}, "nel": {"__e": [[["C", "'", "è", "stato", "un", "piccolo", "incendio", "nel", "mio", "appartamento", "ieri", "sera", ".", "Piccolo", "quanto", "?"], "I had a little fire in my apartment last night."], [["-", "C", "'", "e", "'", "stato", "un", "incendio", "nel", "mio", "cuore", "..."], "There is a fire is my heart.."], [["C", "'", "e", "'", "stato", "un", "piccolo", "incendio", "nel", "bagno", "degli", "uomini", "al", "piano", "di", "sotto", "."], "Um, there was a small fire in the men's room downstairs."]]}, "di": {"__e": [[["Ieri", "notte", ",", "un", "mio", "vecchio", "professore", "è", "morto", "in", "un", "incendio", "di", "laboratorio", "."], "Last night, an old professor of mine died in a lab fire."], [["E", "poi", "un", "paio", "di", "settimane", "fa", "sono", "finito", "in", "un", "...", "incendio", "di", "roba", "chimica", "e", "...", "basta", ",", "ecco", "tutto", "."], "And then a couple weeks ago, I got caught in a.... In a chemical fire. And, well, here we are."], [["-", "C", "'", "e", "'", "stato", "un", "incendio", "di", "te", "'", "."], "So that's what happened."]]}, "nella": {"__e": [[["È", "morto", "da", "poco", "in", "un", "incendio", "nella", "504", "."], "He recently died in a fire in room 504."], [["Tua", "madre", "è", "morta", "allo", "stesso", "modo", ",", "no", "?", "Un", "incendio", "nella", "stanza", "di", "Sam", "?"], "Your mom died the same way, didn't she -- the fire in sam's nursery?"], [["Ha", "perso", "sua", "madre", "in", "un", "incendio", "nella", "camera", "dei", "bambini", "esattamente", "sei", "mesi", "dopo", ",", "proprio", "come", "me", "."], "Lost his mother in a nursery fire exactly six months later, also like me."]]}, "in": {"un": {"__e": [[["C", "'", "e", "'", "un", "incendio", "in", "un", "palazzo", "di", "ghiaccio", ",", "da", "dove", "e", "'", "uscito", "?"], "You have a fire in an ice palace. Where did that come from?"], [["I", "loro", "genitori", "sono", "stati", "uccisi", "da", "un", "incendio", "in", "un", "hotel", "quattro", "anni", "fa", "."], "Very close. Their parents were killed in a hotel fire 4 years ago."], [["No", ",", "ma", "...", "un", "incendio", "in", "un", "magazzino", "?", "Mi", "sembra", "un", "po", "'", "troppo", "per", "qualche", "documento", "."], "No, but... really, a warehouse fire?"]]}, "__e": [[["Tre", "anni", "fa", ",", "un", "incendio", "in", "cucina", "si", "e", "'", "portato", "via", "il", "mio", "bambino", "."], "Two years ago, a kitchen fire claimed the life of my baby boy."], [["C", "'", "e", "stato", "un", "incendio", "in", "casa", "la", "notte", "in", "cui", "il", "bambino", "faceva", "sei", "mesi", "."], "They've all had house fires on the night of the kid's 6-month birthday."], [["C", "'", "e", "'", "stato", "un", "incendio", "in", "una", "delle", "sue", "proprieta", "'", "ieri", "sera", ",", "quindi", "...", "ha", "bisogno", "di", "me", "per", "..."], "He had a fire at one of his real estate properties last night, so he needs me to..."]]}, "a": {"__e": [[["Ok", ",", "sto", "arrivando", ".", "C", "'", "e", "'", "stato", "un", "incendio", "a", "casa", "mia", "."], "Uh, a fire in my place."], [["Ma", "tu", "lo", "sai", "che", "una", "settimana", "fa", "c", "'", "e", "'", "stato", "un", "incendio", "a", "casa", "loro", "?"], "You know there was a fire there a week ago? Sad."], [["Hai", "saputo", "che", "c", "'", "e", "'", "stato", "un", "incendio", "a", "casa", "sua", ",", "la", "scorsa", "notte", "?"], "Did you hear there was a fire at his house - the other night?"]]}, "__l": 4}