{"ikke": {"__e": [[["Han", "var", "fornuftig", "og", "sparsommelig", ".", "Han", "drakk", "ikke", "og", "røykte", "ikke", "."], "He was by all accounts a very sensible, uh, frugal man who didn't drink, didn't smoke, walked everywhere."], [["Han", "røykte", "ikke", "og", "rørte", "ikke", "kaffe", "."], "- Didn't smoke, never touched coffee."], [["-Jeg", "var", "gravid", "og", "røykte", "ikke", "."], "Oh, I was pregnant. I was not smoking."]]}, "og": {"__e": [[["Jeg", "røykte", "og", "drakk", "de", "tre", "første", "månedene", ",", "men", "jeg", "visste", "ikke", "jeg", "var", "gravid", "."], "I smoked and drank during the first three months but I didn't know I was pregnant."], [["På", "skolen", "satt", "vi", "alltid", "på", "sånne", "steder", "og", "røykte", "og", "løy", "om", "gutter", "."], "-They must be. Yeah. You know, in high school... we used to hang out in these things all the time."], [["Vi", "sto", "i", "mørket", "seks", "meter", "unna", "mens", "de", "snakket", ",", "røykte", "og", "laget", "mat", "."], "We stood in the darkness 20 feet away while they talked and smoked and made dinner."]]}, "en": {"__e": [[["Hun", "ble", "sur", "og", "røykte", "en", "rev", "uten", "å", "sende", "den", "rundt", "."], "So she gets uptight. breaks out sone hash and won't give us any."], [["Jeg", "røykte", "en", "stor", "dose", "med", "livet", "før", "jeg", "kom", "på", "jobb", "i", "dag", "."], "Smoked a big old bowl of life before I came in today."], [["En", "venn", "røykte", "en", "rev", "i", "går", ",", "og", "jeg", "hadde", "på", "meg", "den", "buksa", "."], "Last night, my friend had a joint, and I was wearing these jeans."]]}, "du": {"__e": [[["Når", "røykte", "du", "sist", "en", "rev", "?"], "When's the last time you smoked weed?"], [["Du", "trenger", "en", "sigarett", ",", "fordi", "før", "røykte", "du", ",", "men", "har", "sluttet", ",", "med", "unntak", "av", "når", "du", "har", "avsluttet", "en", "bok", "og", "da", "tar", "du", "kun", "én", "."], "You need a cigarette, because you used to smoke but you quit, except when you finish a book, and you have just one."], [["La", "du", "det", "i", "en", "bevispose", "med", "en", "gang", ",", "eller", "røykte", "du", "det", "først", "?"], "Did you bag the pot as evidence as soon as you bought it? Or... did you maybe bring it home and smoke it first?"]]}, "__l": 6}