{"sein": {"oder": {"__e": [[["Das", "soll", "ja", "wohl", "ein", "Witz", "sein", ",", "oder", "?"], "You have got to be kidding me, right?"], [["Soll", "das", "ein", "Witz", "sein", "oder", "was", "?", "Was", "soll", "das", "denn", "werden", "?"], "What are you doing?"], [["Das", "kann", "doch", "nur", "ein", "Witz", "sein", ",", "oder", "?"], "And you're kidding me, right?"]]}, "soll": {"__e": [[["Wenn", "das", "ein", "Witz", "sein", "soll", ",", "verstehe", "ich", "ihn", "nicht", "."], "If this is some sort of a joke I'm afraid I don't see the point."], [["Bitte", "sagen", "Sie", "mir", ",", "dass", "das", "ein", "Witz", "sein", "soll", "."], "Please tell me you're joking."], [["Ich", "weiß", "nicht", ",", "ob", "das", "ein", "Witz", "sein", "soll", ",", "oder", "ob", "das", "Ernst", "ist", "."], "I don't know when you're kidding."]]}, "__e": [[["Bitte", "sagen", "Sie", "mir", ",", "dass", "das", "ein", "Witz", "sein", "soll", "."], "Please tell me you're joking."], [["-", "Ich", "habe", "sie", "nicht", "mehr", ".", "-", "Soll", "das", "ein", "Witz", "sein", "?"], "- I don't have them anymore."], [["Soll", "das", "ein", "Witz", "sein", "oder", "was", "?", "Was", "soll", "das", "denn", "werden", "?"], "What are you doing?"]]}, "ist": {"__e": [[["Ich", "weiß", ",", "dass", "das", "nur", "ein", "Witz", "ist", "."], "I know you're just kidding."], [["Nein", ",", "war", "nur", "ein", "Witz", ",", "ist", "sie", "nicht", "!"], "No, I'm kidding, she's not."], [["Ich", "bin", "mir", "sicher", ",", "er", "weiß", ",", "dass", "es", "kein", "Witz", "ist", "."], "I'm pretty sure he doesn't think it's a joke."]]}, "oder": {"__e": [[["Die", "tun", ",", "als", "sei", "es", "ein", "Witz", "oder", "so", "."], "They're making it out to be a big joke or something."], [["Was", "ist", "das", "?", "Ein", "Witz", "oder", "so", "was", "?"], "What is this, a joke or something?"], [["Für", "dich", "ist", "das", "alles", "ein", "Witz", ",", "oder", "?"], "It's all a joke to you, isn't it?"]]}, "gemacht": {"__e": [[["-", "Nein", ",", "das", "...", "ich", "habe", "nur", "einen", "Witz", "gemacht", "."], "No, that was... I was joking."], [["Nein", ",", "nein", ",", "ich", "hab", ",", "ich", "habe", "nur", "einen", "Witz", "gemacht", "."], "No, no, I was... I was making a joke."], [["Ich", "weiß", "nicht", ",", "wieso", "ich", "jetzt", "einen", "Witz", "gemacht", "habe", "."], "I don't know why- I don't know why I made a joke."]]}, "über": {"__e": [[["Ich", "wollte", "einen", "Witz", "über", "ihn", "machen", "."], "I was trying to make a joke about my eggs."], [["Gestern", "Nacht", "hat", "sie", "einen", "Witz", "über", "mich", "gemacht", ",", "ich", "würde", "2+"], "I mean, last night, she made a joke about me doing B-plus work, but so what?"], [["-", "Ist", "das", "ein", "Witz", "über", "meine", "Mutter", "?"], "- You gonna make fun of my mother, too?"]]}, "für": {"dich": {"__e": [[["-", "Hey", ",", "jetzt", "bin", "ich", "mal", "dran", ".", "ich", "hab", "einen", "Witz", "für", "dich", "."], "Hey, Howard, let me ask you a question. I got a riddle for you."], [["Ist", "das", "alles", "nur", "ein", "Witz", "für", "dich", "?"], "Is this all a joke to you?"], [["Das", "ist", "alles", "nur", "ein", "Witz", "für", "dich", "?"], "So, this is all just a joke to you?"]]}, "sie": {"__e": [[["Ich", "hatte", "noch", "einen", "Witz", "für", "sie", "."], "I h-had a joke to tell her."], [["Das", "ist", "ein", "Witz", "für", "Sie", "."], "This is a joke to you."], [["Ist", "das", "ein", "Witz", "für", "Sie", "?"], "Is this a fucking joke to you?"]]}, "__e": [[["Das", "ist", "alles", "nur", "ein", "Witz", "für", "dich", "?"], "So, this is all just a joke to you?"], [["Ist", "das", "alles", "nur", "ein", "Witz", "für", "dich", "?"], "Is this all a joke to you?"], [["Seit", "ich", "hier", "bin", ",", "war", "ich", "nichts", "als", "ein", "Witz", "für", "euch", "."], "The whole time I've been here I've been nothing but a joke to you guys."]]}, "__l": 3}